floret_pybind.cpython-39-darwin.so
floret-0.10.5.dist-info/RECORD
floret-0.10.5.dist-info/LICENSE
floret-0.10.5.dist-info/WHEEL
floret-0.10.5.dist-info/top_level.txt
floret-0.10.5.dist-info/METADATA
floret/__init__.py
floret/floret.py
floret/util/util.py
floret/util/__init__.py
floret/tests/test_train.py
floret/tests/test_script.py
floret/tests/__init__.py
floret/tests/README.md
floret/tests/test_tokenize.py
floret/tests/data.txt
floret/tests/test_configurations.py
